open_actuator/__init__.py
open_actuator-0.1.0.dist-info/licenses/LICENSE
open_actuator-0.1.0.dist-info/METADATA
open_actuator-0.1.0.dist-info/WHEEL
open_actuator-0.1.0.dist-info/top_level.txt
open_actuator-0.1.0.dist-info/RECORD
